extras/__init__.py
extras/f2.py
om_testing_package-0.0.1.dist-info/METADATA
om_testing_package-0.0.1.dist-info/WHEEL
om_testing_package-0.0.1.dist-info/top_level.txt
om_testing_package-0.0.1.dist-info/RECORD
